{"cameraMode":{"drawMode":0,"name":"Shaded","section":"Shading Mode"},"sceneLighting":true,"audioPlay":false,"sceneViewState":{"m_AlwaysRefresh":false,"showFog":true,"showSkybox":true,"showFlares":true,"showImageEffects":true,"showParticleSystems":true,"showVisualEffectGraphs":true,"m_FxEnabled":true},"in2DMode":false,"pivot":{"x":-1.3000001907348633,"y":12.319999694824219,"z":-24.209999084472658},"rotation":{"x":-0.2435770481824875,"y":-0.2810778021812439,"z":0.07399159669876099,"w":-0.9253137707710266},"size":12.12435531616211,"orthographic":false}